analytics/__init__.py
analytics/investment_statistics.py
analytics/statistics.py
investments/__init__.py
investments/calculator.py
introtopython_feb26_lizh_finance_tools-0.4.0.dist-info/METADATA
introtopython_feb26_lizh_finance_tools-0.4.0.dist-info/WHEEL
introtopython_feb26_lizh_finance_tools-0.4.0.dist-info/top_level.txt
introtopython_feb26_lizh_finance_tools-0.4.0.dist-info/RECORD
