Metadata-Version: 2.2
Name: introtopython-feb26-lizh-finance-tools
Version: 0.4.0
Summary: A collection of tools for financial analysis
Author: Liz Howard
License: MIT
Requires-Dist: numpy
Requires-Dist: pandas
Dynamic: author
Dynamic: license
Dynamic: requires-dist
Dynamic: summary
